bullet_point_adder.py
auto_guild-1.0.1.dist-info/entry_points.txt
auto_guild-1.0.1.dist-info/WHEEL
auto_guild-1.0.1.dist-info/METADATA
auto_guild-1.0.1.dist-info/license_files/LICENSE
auto_guild-1.0.1.dist-info/RECORD
