Metadata-Version: 2.1
Name: auto_guild
Version: 1.0.1
Summary: Creates a Discord server based on a template you layout, making it an easy and quick way to flesh out a server to fit your needs.
License: MIT
Author-email: Daniel J Brown <browndj3@gmail.com>
Requires-Python: >=3.7
Requires-Dist: python-dotenv>=0.20.0
Requires-Dist: pyyaml>=6.0
Requires-Dist: requests>=2.27.1
Project-URL: homepage, https://github.com/MrHemlock/auto_guild
Project-URL: repository, https://github.com/MrHemlock/auto_guild
